add_memory/__init__.py
add_memory/constants.py
add_memory/memory_functions.py
add_memory/watsonx_assistant_service.py
add_memory-1.0.2.dist-info/METADATA
add_memory-1.0.2.dist-info/WHEEL
add_memory-1.0.2.dist-info/top_level.txt
add_memory-1.0.2.dist-info/RECORD
