Metadata-Version: 2.1
Name: add-memory
Version: 1.0.2
Summary: Library to manage conversational memory using Watsonx Assistant Session API
Home-page: UNKNOWN
Author: tskvivekmani
License: UNKNOWN
Platform: UNKNOWN
Requires-Dist: ibm-watson (>=7.0.1)
